pyorcid/__init__.py
pyorcid/orcid.py
pyorcid/orcid_authentication.py
pyorcid/orcid_scrapper.py
pyorcid/orcid_search.py
pyorcid-1.2.2.dist-info/licenses/LICENSE
pyorcid-1.2.2.dist-info/METADATA
pyorcid-1.2.2.dist-info/WHEEL
pyorcid-1.2.2.dist-info/RECORD
