Metadata-Version: 2.4
Name: PyOrcid
Version: 1.2.2
Summary: API client for ORCID API
License: MIT
License-File: LICENSE
Keywords: orcid,orcid-api,pyorcid
Author: Sriram Seelamneni
Author-email: srirams0606@gmail.com
Requires-Python: >=3.9
Classifier: License :: OSI Approved :: MIT License
Classifier: Programming Language :: Python
Classifier: Programming Language :: Python :: 3
Classifier: Programming Language :: Python :: 3.9
Classifier: Programming Language :: Python :: 3.10
Classifier: Programming Language :: Python :: 3.11
Classifier: Programming Language :: Python :: 3.12
Classifier: Programming Language :: Python :: 3.13
Classifier: Programming Language :: Python :: 3.14
Requires-Dist: certifi (>=2024.0.0)
Requires-Dist: python-dotenv
Requires-Dist: requests (>=2.26.0,<3.0.0)
Requires-Dist: urllib3 (>=1.26.7,<3.0.0)
Requires-Dist: xmltodict
Project-URL: Repository, https://github.com/sri0606/PyOrcid
